{
"Student1": {
   "name":"rajiv",
   "rollNumber":"KV2017-5A2",
   "marks":{
   "Maths":"18",
   "English":"21",
   "Science":"45"
   }        
   },
"Student2": {
   "name":"abhishek",
   "rollNumber":"KV2017-5A1",
   "marks":{
   "Maths":"43",
   "English":"30",
   "Science":"37"
   }        
   },
"Student3": {
   "name":"zoya",
   "rollNumber":"KV2017-5A3",
   "marks":{
   "Maths":"42",
   "English":"31",
   "Science":"50"
   }
   },
"Student4": {
   "name":"rajiv",
   "rollNumber":"KV2017-5A2",
   "marks":{
   "Maths":"18",
   "English":"21",
   "Science":"45"
   }        
   },
"Student5": {
   "name":"abhishek",
   "rollNumber":"KV2017-5A1",
   "marks":{
   "Maths":"43",
   "English":"30",
   "Science":"37"
   }        
   },
"Student6": {
   "name":"zoya",
   "rollNumber":"KV2017-5A3",
   "marks":{
   "Maths":"42",
   "English":"31",
   "Science":"50"
   }
   },
"Student7": {
   "name":"rajiv",
   "rollNumber":"KV2017-5A2",
   "marks":{
   "Maths":"18",
   "English":"21",
   "Science":"45"
   }        
   },
"Student8": {
   "name":"abhishek",
   "rollNumber":"KV2017-5A1",
   "marks":{
   "Maths":"43",
   "English":"30",
   "Science":"37"
   }        
   },
"Student9": {
   "name":"zoya",
   "rollNumber":"KV2017-5A3",
   "marks":{
   "Maths":"42",
   "English":"31",
   "Science":"50"
   }
   },
"Student10": {
   "name":"rajiv",
   "rollNumber":"KV2017-5A2",
   "marks":{
   "Maths":"18",
   "English":"21",
   "Science":"45"
   }        
   },
"Student11": {
   "name":"abhishek",
   "rollNumber":"KV2017-5A1",
   "marks":{
   "Maths":"43",
   "English":"30",
   "Science":"37"
   }        
   },
"Student12": {
   "name":"zoya",
   "rollNumber":"KV2017-5A3",
   "marks":{
   "Maths":"42",
   "English":"31",
   "Science":"50"
   }
   },
"Student13": {
   "name":"rajiv",
   "rollNumber":"KV2017-5A2",
   "marks":{
   "Maths":"18",
   "English":"21",
   "Science":"45"
   }        
   },
"Student14": {
   "name":"abhishek",
   "rollNumber":"KV2017-5A1",
   "marks":{
   "Maths":"43",
   "English":"30",
   "Science":"37"
   }        
   },
"Student15": {
   "name":"zoya",
   "rollNumber":"KV2017-5A3",
   "marks":{
   "Maths":"42",
   "English":"31",
   "Science":"50"
   }
   }
}
